admiral/__init__.py
admiral/jobmanagers.py
admiral/remote.py
admiral/slurm.py
admiral/support.py
admiral-0.2.dist-info/METADATA
admiral-0.2.dist-info/RECORD
admiral-0.2.dist-info/WHEEL
admiral-0.2.dist-info/top_level.txt
